{"game":{"gameId":"0021700039","gameCode":"20171022/MINOKC","gameStatus":3,"gameStatusText":"Final","period":4,"gameClock":"PT00M00.00S","gameTimeUTC":"2017-10-22T23:00:00Z","gameEt":"2017-10-22T19:00:00Z","awayTeamId":1610612750,"homeTeamId":1610612760,"duration":"2:15","attendance":18203,"sellout":1,"seriesGameNumber":"","gameLabel":"","gameSubLabel":"","seriesText":"","ifNecessary":false,"isNeutral":null,"arena":{"arenaId":196,"arenaName":"Chesapeake Energy Arena","arenaCity":"Oklahoma City","arenaState":"OK","arenaCountry":"US","arenaTimezone":"Central","arenaStreetAddress":"100 W Reno Ave","arenaPostalCode":"73102"},"officials":[{"personId":1664,"name":"Gary Zielinski","nameI":"G. Zielinski","firstName":"Gary","familyName":"Zielinski","jerseyNum":"59","assignment":""},{"personId":1199,"name":"Tom Washington","nameI":"T. Washington","firstName":"Tom","familyName":"Washington","jerseyNum":"49","assignment":""},{"personId":1627964,"name":"Jonathan Sterling","nameI":"J. Sterling","firstName":"Jonathan","familyName":"Sterling","jerseyNum":"17","assignment":""}],"broadcasters":{"nationalBroadcasters":[],"nationalRadioBroadcasters":[],"nationalOttBroadcasters":[],"homeTvBroadcasters":[{"broadcasterId":1136,"broadcastDisplay":"FSOK","broadcasterDisplay":"Fox Sports Oklahoma","broadcasterVideoLink":"","broadcasterDescription":null,"broadcasterTeamId":1610612760}],"homeRadioBroadcasters":[{"broadcasterId":1140,"broadcastDisplay":"WWLS","broadcasterDisplay":"WWLS 98.1FM OKC","broadcasterVideoLink":"","broadcasterDescription":null,"broadcasterTeamId":1610612760}],"homeOttBroadcasters":[],"awayTvBroadcasters":[{"broadcasterId":157,"broadcastDisplay":"FSNTH","broadcasterDisplay":"Fox Sports North","broadcasterVideoLink":"","broadcasterDescription":null,"broadcasterTeamId":1610612750}],"awayRadioBroadcasters":[{"broadcasterId":1380,"broadcastDisplay":"WCCO","broadcasterDisplay":"830 WCCO","broadcasterVideoLink":"","broadcasterDescription":null,"broadcasterTeamId":1610612750}],"awayOttBroadcasters":[]},"homeTeam":{"teamId":1610612760,"teamName":"Thunder","teamCity":"Oklahoma City","teamTricode":"OKC","teamSlug":"thunder","teamWins":1,"teamLosses":2,"score":113,"inBonus":"","timeoutsRemaining":0,"seed":0,"statistics":{"minutes":"240:00","fieldGoalsMade":46,"fieldGoalsAttempted":96,"fieldGoalsPercentage":0.479,"threePointersMade":11,"threePointersAttempted":31,"threePointersPercentage":0.355,"freeThrowsMade":10,"freeThrowsAttempted":16,"freeThrowsPercentage":0.625,"reboundsOffensive":9,"reboundsDefensive":27,"reboundsTotal":36,"assists":26,"steals":9,"blocks":6,"turnovers":11,"foulsPersonal":22,"points":113,"plusMinusPoints":-2},"periods":[{"period":1,"periodType":"REGULAR","score":23},{"period":2,"periodType":"REGULAR","score":31},{"period":3,"periodType":"REGULAR","score":21},{"period":4,"periodType":"REGULAR","score":38}],"players":[{"personId":202331,"firstName":"Paul","familyName":"George","nameI":"P. George","playerSlug":"paul-george","position":"F","comment":"","jerseyNum":"","statistics":{"minutes":"37:27","fieldGoalsMade":6,"fieldGoalsAttempted":20,"fieldGoalsPercentage":0.3,"threePointersMade":1,"threePointersAttempted":8,"threePointersPercentage":0.125,"freeThrowsMade":1,"freeThrowsAttempted":1,"freeThrowsPercentage":1,"reboundsOffensive":0,"reboundsDefensive":6,"reboundsTotal":6,"assists":8,"steals":4,"blocks":0,"turnovers":2,"foulsPersonal":4,"points":14,"plusMinusPoints":-4}},{"personId":2546,"firstName":"Carmelo","familyName":"Anthony","nameI":"C. Anthony","playerSlug":"carmelo-anthony","position":"F","comment":"","jerseyNum":"","statistics":{"minutes":"37:02","fieldGoalsMade":9,"fieldGoalsAttempted":19,"fieldGoalsPercentage":0.474,"threePointersMade":2,"threePointersAttempted":7,"threePointersPercentage":0.286,"freeThrowsMade":3,"freeThrowsAttempted":3,"freeThrowsPercentage":1,"reboundsOffensive":0,"reboundsDefensive":2,"reboundsTotal":2,"assists":2,"steals":3,"blocks":0,"turnovers":2,"foulsPersonal":3,"points":23,"plusMinusPoints":12}},{"personId":203500,"firstName":"Steven","familyName":"Adams","nameI":"S. Adams","playerSlug":"steven-adams","position":"C","comment":"","jerseyNum":"","statistics":{"minutes":"34:56","fieldGoalsMade":8,"fieldGoalsAttempted":12,"fieldGoalsPercentage":0.667,"threePointersMade":0,"threePointersAttempted":0,"threePointersPercentage":0,"freeThrowsMade":1,"freeThrowsAttempted":1,"freeThrowsPercentage":1,"reboundsOffensive":8,"reboundsDefensive":5,"reboundsTotal":13,"assists":3,"steals":1,"blocks":2,"turnovers":2,"foulsPersonal":1,"points":17,"plusMinusPoints":-17}},{"personId":203460,"firstName":"Andre","familyName":"Roberson","nameI":"A. Roberson","playerSlug":"andre-roberson","position":"G","comment":"","jerseyNum":"","statistics":{"minutes":"22:05","fieldGoalsMade":0,"fieldGoalsAttempted":4,"fieldGoalsPercentage":0,"threePointersMade":0,"threePointersAttempted":2,"threePointersPercentage":0,"freeThrowsMade":0,"freeThrowsAttempted":2,"freeThrowsPercentage":0,"reboundsOffensive":0,"reboundsDefensive":1,"reboundsTotal":1,"assists":0,"steals":0,"blocks":0,"turnovers":1,"foulsPersonal":2,"points":0,"plusMinusPoints":-21}},{"personId":201566,"firstName":"Russell","familyName":"Westbrook","nameI":"R. Westbrook","playerSlug":"russell-westbrook","position":"G","comment":"","jerseyNum":"","statistics":{"minutes":"36:31","fieldGoalsMade":12,"fieldGoalsAttempted":24,"fieldGoalsPercentage":0.5,"threePointersMade":5,"threePointersAttempted":8,"threePointersPercentage":0.625,"freeThrowsMade":2,"freeThrowsAttempted":4,"freeThrowsPercentage":0.5,"reboundsOffensive":0,"reboundsDefensive":5,"reboundsTotal":5,"assists":10,"steals":0,"blocks":1,"turnovers":2,"foulsPersonal":0,"points":31,"plusMinusPoints":-17}},{"personId":203924,"firstName":"Jerami","familyName":"Grant","nameI":"J. Grant","playerSlug":"jerami-grant","position":"","comment":"","jerseyNum":"","statistics":{"minutes":"19:24","fieldGoalsMade":4,"fieldGoalsAttempted":5,"fieldGoalsPercentage":0.8,"threePointersMade":1,"threePointersAttempted":1,"threePointersPercentage":1,"freeThrowsMade":3,"freeThrowsAttempted":5,"freeThrowsPercentage":0.6,"reboundsOffensive":1,"reboundsDefensive":3,"reboundsTotal":4,"assists":0,"steals":0,"blocks":1,"turnovers":1,"foulsPersonal":1,"points":12,"plusMinusPoints":7}},{"personId":203518,"firstName":"Alex","familyName":"Abrines","nameI":"A. Abrines","playerSlug":"alex-abrines","position":"","comment":"","jerseyNum":"","statistics":{"minutes":"14:20","fieldGoalsMade":2,"fieldGoalsAttempted":2,"fieldGoalsPercentage":1,"threePointersMade":0,"threePointersAttempted":0,"threePointersPercentage":0,"freeThrowsMade":0,"freeThrowsAttempted":0,"freeThrowsPercentage":0,"reboundsOffensive":0,"reboundsDefensive":0,"reboundsTotal":0,"assists":0,"steals":1,"blocks":0,"turnovers":0,"foulsPersonal":4,"points":4,"plusMinusPoints":13}},{"personId":101109,"firstName":"Raymond","familyName":"Felton","nameI":"R. Felton","playerSlug":"raymond-felton","position":"","comment":"","jerseyNum":"","statistics":{"minutes":"18:15","fieldGoalsMade":5,"fieldGoalsAttempted":7,"fieldGoalsPercentage":0.714,"threePointersMade":2,"threePointersAttempted":3,"threePointersPercentage":0.667,"freeThrowsMade":0,"freeThrowsAttempted":0,"freeThrowsPercentage":0,"reboundsOffensive":0,"reboundsDefensive":1,"reboundsTotal":1,"assists":2,"steals":0,"blocks":0,"turnovers":1,"foulsPersonal":4,"points":12,"plusMinusPoints":23}},{"personId":203962,"firstName":"Josh","familyName":"Huestis","nameI":"J. Huestis","playerSlug":"josh-huestis","position":"","comment":"","jerseyNum":"","statistics":{"minutes":"14:10","fieldGoalsMade":0,"fieldGoalsAttempted":1,"fieldGoalsPercentage":0,"threePointersMade":0,"threePointersAttempted":0,"threePointersPercentage":0,"freeThrowsMade":0,"freeThrowsAttempted":0,"freeThrowsPercentage":0,"reboundsOffensive":0,"reboundsDefensive":4,"reboundsTotal":4,"assists":1,"steals":0,"blocks":2,"turnovers":0,"foulsPersonal":2,"points":0,"plusMinusPoints":0}},{"personId":202335,"firstName":"Patrick","familyName":"Patterson","nameI":"P. Patterson","playerSlug":"patrick-patterson","position":"","comment":"","jerseyNum":"","statistics":{"minutes":"5:50","fieldGoalsMade":0,"fieldGoalsAttempted":2,"fieldGoalsPercentage":0,"threePointersMade":0,"threePointersAttempted":2,"threePointersPercentage":0,"freeThrowsMade":0,"freeThrowsAttempted":0,"freeThrowsPercentage":0,"reboundsOffensive":0,"reboundsDefensive":0,"reboundsTotal":0,"assists":0,"steals":0,"blocks":0,"turnovers":0,"foulsPersonal":1,"points":0,"plusMinusPoints":-6}},{"personId":2555,"firstName":"Nick","familyName":"Collison","nameI":"N. Collison","playerSlug":"nick-collison","position":"","comment":"DNP - Coach's Decision","jerseyNum":"","statistics":{"minutes":"","fieldGoalsMade":0,"fieldGoalsAttempted":0,"fieldGoalsPercentage":0,"threePointersMade":0,"threePointersAttempted":0,"threePointersPercentage":0,"freeThrowsMade":0,"freeThrowsAttempted":0,"freeThrowsPercentage":0,"reboundsOffensive":0,"reboundsDefensive":0,"reboundsTotal":0,"assists":0,"steals":0,"blocks":0,"turnovers":0,"foulsPersonal":0,"points":0,"plusMinusPoints":0}},{"personId":1628390,"firstName":"Terrance","familyName":"Ferguson","nameI":"T. Ferguson","playerSlug":"terrance-ferguson","position":"","comment":"DNP - Coach's Decision","jerseyNum":"","statistics":{"minutes":"","fieldGoalsMade":0,"fieldGoalsAttempted":0,"fieldGoalsPercentage":0,"threePointersMade":0,"threePointersAttempted":0,"threePointersPercentage":0,"freeThrowsMade":0,"freeThrowsAttempted":0,"freeThrowsPercentage":0,"reboundsOffensive":0,"reboundsDefensive":0,"reboundsTotal":0,"assists":0,"steals":0,"blocks":0,"turnovers":0,"foulsPersonal":0,"points":0,"plusMinusPoints":0}},{"personId":1626177,"firstName":"Dakari","familyName":"Johnson","nameI":"D. Johnson","playerSlug":"dakari-johnson","position":"","comment":"DNP - Coach's Decision","jerseyNum":"","statistics":{"minutes":"","fieldGoalsMade":0,"fieldGoalsAttempted":0,"fieldGoalsPercentage":0,"threePointersMade":0,"threePointersAttempted":0,"threePointersPercentage":0,"freeThrowsMade":0,"freeThrowsAttempted":0,"freeThrowsPercentage":0,"reboundsOffensive":0,"reboundsDefensive":0,"reboundsTotal":0,"assists":0,"steals":0,"blocks":0,"turnovers":0,"foulsPersonal":0,"points":0,"plusMinusPoints":0}}],"inactives":[{"personId":1627772,"firstName":"Daniel","familyName":"Hamilton","jerseyNum":"25"},{"personId":1628408,"firstName":"PJ","familyName":"Dozier","jerseyNum":"35"},{"personId":202713,"firstName":"Kyle","familyName":"Singler","jerseyNum":"15"}],"starters":{"minutes":"168:01","fieldGoalsMade":35,"fieldGoalsAttempted":79,"fieldGoalsPercentage":0.443,"threePointersMade":8,"threePointersAttempted":25,"threePointersPercentage":0.32,"freeThrowsMade":7,"freeThrowsAttempted":11,"freeThrowsPercentage":0.636,"reboundsOffensive":8,"reboundsDefensive":19,"reboundsTotal":27,"assists":23,"steals":8,"blocks":3,"turnovers":9,"foulsPersonal":10,"points":85},"bench":{"minutes":"168:01","fieldGoalsMade":11,"fieldGoalsAttempted":17,"fieldGoalsPercentage":0.647,"threePointersMade":3,"threePointersAttempted":6,"threePointersPercentage":0.5,"freeThrowsMade":3,"freeThrowsAttempted":5,"freeThrowsPercentage":0.6,"reboundsOffensive":1,"reboundsDefensive":8,"reboundsTotal":9,"assists":3,"steals":1,"blocks":3,"turnovers":2,"foulsPersonal":12,"points":28}},"awayTeam":{"teamId":1610612750,"teamName":"Timberwolves","teamCity":"Minnesota","teamTricode":"MIN","teamSlug":"timberwolves","teamWins":2,"teamLosses":1,"score":115,"inBonus":"","timeoutsRemaining":0,"seed":0,"statistics":{"minutes":"240:00","fieldGoalsMade":43,"fieldGoalsAttempted":86,"fieldGoalsPercentage":0.5,"threePointersMade":10,"threePointersAttempted":25,"threePointersPercentage":0.4,"freeThrowsMade":19,"freeThrowsAttempted":23,"freeThrowsPercentage":0.826,"reboundsOffensive":10,"reboundsDefensive":35,"reboundsTotal":45,"assists":25,"steals":5,"blocks":1,"turnovers":17,"foulsPersonal":17,"points":115,"plusMinusPoints":2},"periods":[{"period":1,"periodType":"REGULAR","score":28},{"period":2,"periodType":"REGULAR","score":33},{"period":3,"periodType":"REGULAR","score":27},{"period":4,"periodType":"REGULAR","score":27}],"players":[{"personId":203952,"firstName":"Andrew","familyName":"Wiggins","nameI":"A. Wiggins","playerSlug":"andrew-wiggins","position":"F","comment":"","jerseyNum":"","statistics":{"minutes":"39:24","fieldGoalsMade":10,"fieldGoalsAttempted":20,"fieldGoalsPercentage":0.5,"threePointersMade":2,"threePointersAttempted":7,"threePointersPercentage":0.286,"freeThrowsMade":5,"freeThrowsAttempted":8,"freeThrowsPercentage":0.625,"reboundsOffensive":1,"reboundsDefensive":6,"reboundsTotal":7,"assists":4,"steals":2,"blocks":0,"turnovers":1,"foulsPersonal":2,"points":27,"plusMinusPoints":15}},{"personId":201959,"firstName":"Taj","familyName":"Gibson","nameI":"T. Gibson","playerSlug":"taj-gibson","position":"F","comment":"","jerseyNum":"","statistics":{"minutes":"33:12","fieldGoalsMade":5,"fieldGoalsAttempted":7,"fieldGoalsPercentage":0.714,"threePointersMade":1,"threePointersAttempted":1,"threePointersPercentage":1,"freeThrowsMade":0,"freeThrowsAttempted":0,"freeThrowsPercentage":0,"reboundsOffensive":2,"reboundsDefensive":8,"reboundsTotal":10,"assists":2,"steals":1,"blocks":0,"turnovers":4,"foulsPersonal":0,"points":11,"plusMinusPoints":21}},{"personId":1626157,"firstName":"Karl-Anthony","familyName":"Towns","nameI":"K. Towns","playerSlug":"karl-anthony-towns","position":"C","comment":"","jerseyNum":"","statistics":{"minutes":"35:35","fieldGoalsMade":11,"fieldGoalsAttempted":17,"fieldGoalsPercentage":0.647,"threePointersMade":2,"threePointersAttempted":7,"threePointersPercentage":0.286,"freeThrowsMade":3,"freeThrowsAttempted":3,"freeThrowsPercentage":1,"reboundsOffensive":4,"reboundsDefensive":8,"reboundsTotal":12,"assists":1,"steals":0,"blocks":1,"turnovers":4,"foulsPersonal":5,"points":27,"plusMinusPoints":2}},{"personId":202710,"firstName":"Jimmy","familyName":"Butler III","nameI":"J. Butler III","playerSlug":"jimmy-butler-iii","position":"G","comment":"","jerseyNum":"","statistics":{"minutes":"39:10","fieldGoalsMade":7,"fieldGoalsAttempted":17,"fieldGoalsPercentage":0.412,"threePointersMade":1,"threePointersAttempted":4,"threePointersPercentage":0.25,"freeThrowsMade":0,"freeThrowsAttempted":0,"freeThrowsPercentage":0,"reboundsOffensive":0,"reboundsDefensive":6,"reboundsTotal":6,"assists":6,"steals":0,"blocks":0,"turnovers":1,"foulsPersonal":2,"points":15,"plusMinusPoints":10}},{"personId":201952,"firstName":"Jeff","familyName":"Teague","nameI":"J. Teague","playerSlug":"jeff-teague","position":"G","comment":"","jerseyNum":"","statistics":{"minutes":"39:12","fieldGoalsMade":5,"fieldGoalsAttempted":10,"fieldGoalsPercentage":0.5,"threePointersMade":1,"threePointersAttempted":1,"threePointersPercentage":1,"freeThrowsMade":8,"freeThrowsAttempted":8,"freeThrowsPercentage":1,"reboundsOffensive":1,"reboundsDefensive":5,"reboundsTotal":6,"assists":9,"steals":1,"blocks":0,"turnovers":3,"foulsPersonal":2,"points":19,"plusMinusPoints":14}},{"personId":203476,"firstName":"Gorgui","familyName":"Dieng","nameI":"G. Dieng","playerSlug":"gorgui-dieng","position":"","comment":"","jerseyNum":"","statistics":{"minutes":"12:25","fieldGoalsMade":2,"fieldGoalsAttempted":6,"fieldGoalsPercentage":0.333,"threePointersMade":1,"threePointersAttempted":2,"threePointersPercentage":0.5,"freeThrowsMade":2,"freeThrowsAttempted":2,"freeThrowsPercentage":1,"reboundsOffensive":2,"reboundsDefensive":1,"reboundsTotal":3,"assists":1,"steals":0,"blocks":0,"turnovers":1,"foulsPersonal":2,"points":7,"plusMinusPoints":0}},{"personId":202357,"firstName":"Nemanja","familyName":"Bjelica","nameI":"N. Bjelica","playerSlug":"nemanja-bjelica","position":"","comment":"","jerseyNum":"","statistics":{"minutes":"8:50","fieldGoalsMade":1,"fieldGoalsAttempted":1,"fieldGoalsPercentage":1,"threePointersMade":1,"threePointersAttempted":1,"threePointersPercentage":1,"freeThrowsMade":0,"freeThrowsAttempted":0,"freeThrowsPercentage":0,"reboundsOffensive":0,"reboundsDefensive":1,"reboundsTotal":1,"assists":0,"steals":0,"blocks":0,"turnovers":1,"foulsPersonal":0,"points":3,"plusMinusPoints":-8}},{"personId":2037,"firstName":"Jamal","familyName":"Crawford","nameI":"J. Crawford","playerSlug":"jamal-crawford","position":"","comment":"","jerseyNum":"","statistics":{"minutes":"15:41","fieldGoalsMade":1,"fieldGoalsAttempted":6,"fieldGoalsPercentage":0.167,"threePointersMade":1,"threePointersAttempted":2,"threePointersPercentage":0.5,"freeThrowsMade":0,"freeThrowsAttempted":0,"freeThrowsPercentage":0,"reboundsOffensive":0,"reboundsDefensive":0,"reboundsTotal":0,"assists":2,"steals":0,"blocks":0,"turnovers":1,"foulsPersonal":2,"points":3,"plusMinusPoints":-19}},{"personId":1626145,"firstName":"Tyus","familyName":"Jones","nameI":"T. Jones","playerSlug":"tyus-jones","position":"","comment":"","jerseyNum":"","statistics":{"minutes":"8:48","fieldGoalsMade":0,"fieldGoalsAttempted":0,"fieldGoalsPercentage":0,"threePointersMade":0,"threePointersAttempted":0,"threePointersPercentage":0,"freeThrowsMade":1,"freeThrowsAttempted":2,"freeThrowsPercentage":0.5,"reboundsOffensive":0,"reboundsDefensive":0,"reboundsTotal":0,"assists":0,"steals":1,"blocks":0,"turnovers":1,"foulsPersonal":2,"points":1,"plusMinusPoints":-12}},{"personId":203498,"firstName":"Shabazz","familyName":"Muhammad","nameI":"S. Muhammad","playerSlug":"shabazz-muhammad","position":"","comment":"","jerseyNum":"","statistics":{"minutes":"7:44","fieldGoalsMade":1,"fieldGoalsAttempted":2,"fieldGoalsPercentage":0.5,"threePointersMade":0,"threePointersAttempted":0,"threePointersPercentage":0,"freeThrowsMade":0,"freeThrowsAttempted":0,"freeThrowsPercentage":0,"reboundsOffensive":0,"reboundsDefensive":0,"reboundsTotal":0,"assists":0,"steals":0,"blocks":0,"turnovers":0,"foulsPersonal":0,"points":2,"plusMinusPoints":-13}},{"personId":202332,"firstName":"Cole","familyName":"Aldrich","nameI":"C. Aldrich","playerSlug":"cole-aldrich","position":"","comment":"DNP - Coach's Decision","jerseyNum":"","statistics":{"minutes":"","fieldGoalsMade":0,"fieldGoalsAttempted":0,"fieldGoalsPercentage":0,"threePointersMade":0,"threePointersAttempted":0,"threePointersPercentage":0,"freeThrowsMade":0,"freeThrowsAttempted":0,"freeThrowsPercentage":0,"reboundsOffensive":0,"reboundsDefensive":0,"reboundsTotal":0,"assists":0,"steals":0,"blocks":0,"turnovers":0,"foulsPersonal":0,"points":0,"plusMinusPoints":0}},{"personId":201166,"firstName":"Aaron","familyName":"Brooks","nameI":"A. Brooks","playerSlug":"aaron-brooks","position":"","comment":"DNP - Coach's Decision","jerseyNum":"","statistics":{"minutes":"","fieldGoalsMade":0,"fieldGoalsAttempted":0,"fieldGoalsPercentage":0,"threePointersMade":0,"threePointersAttempted":0,"threePointersPercentage":0,"freeThrowsMade":0,"freeThrowsAttempted":0,"freeThrowsPercentage":0,"reboundsOffensive":0,"reboundsDefensive":0,"reboundsTotal":0,"assists":0,"steals":0,"blocks":0,"turnovers":0,"foulsPersonal":0,"points":0,"plusMinusPoints":0}},{"personId":1627875,"firstName":"Marcus","familyName":"Georges-Hunt","nameI":"M. Georges-Hunt","playerSlug":"marcus-georges-hunt","position":"","comment":"DNP - Coach's Decision","jerseyNum":"","statistics":{"minutes":"","fieldGoalsMade":0,"fieldGoalsAttempted":0,"fieldGoalsPercentage":0,"threePointersMade":0,"threePointersAttempted":0,"threePointersPercentage":0,"freeThrowsMade":0,"freeThrowsAttempted":0,"freeThrowsPercentage":0,"reboundsOffensive":0,"reboundsDefensive":0,"reboundsTotal":0,"assists":0,"steals":0,"blocks":0,"turnovers":0,"foulsPersonal":0,"points":0,"plusMinusPoints":0}}],"inactives":[{"personId":1628383,"firstName":"Justin","familyName":"Patton","jerseyNum":"24"},{"personId":1626148,"firstName":"Anthony","familyName":"Brown","jerseyNum":"3"}],"starters":{"minutes":"186:33","fieldGoalsMade":38,"fieldGoalsAttempted":71,"fieldGoalsPercentage":0.535,"threePointersMade":7,"threePointersAttempted":20,"threePointersPercentage":0.35,"freeThrowsMade":16,"freeThrowsAttempted":19,"freeThrowsPercentage":0.842,"reboundsOffensive":8,"reboundsDefensive":33,"reboundsTotal":41,"assists":22,"steals":4,"blocks":1,"turnovers":13,"foulsPersonal":11,"points":99},"bench":{"minutes":"186:33","fieldGoalsMade":5,"fieldGoalsAttempted":15,"fieldGoalsPercentage":0.333,"threePointersMade":3,"threePointersAttempted":5,"threePointersPercentage":0.6,"freeThrowsMade":3,"freeThrowsAttempted":4,"freeThrowsPercentage":0.75,"reboundsOffensive":2,"reboundsDefensive":2,"reboundsTotal":4,"assists":3,"steals":1,"blocks":0,"turnovers":4,"foulsPersonal":6,"points":16}},"lastFiveMeetings":{"meetings":[{"recencyOrder":1,"gameId":"0021601213","gameTimeUTC":"2017-04-12T00:00:00Z","gameEt":"2017-04-11T20:00:00Z","gameStatus":3,"gameStatusText":"Final","gameClock":"PT00M00.00S","broadcasterVideoLink":null,"awayTeam":{"teamId":1610612760,"teamCity":"Oklahoma City","teamName":"Thunder","teamTricode":"OKC","teamSlug":"thunder","score":100,"wins":47,"losses":34},"homeTeam":{"teamId":1610612750,"teamCity":"Minnesota","teamName":"Timberwolves","teamTricode":"MIN","teamSlug":"timberwolves","score":98,"wins":31,"losses":50}},{"recencyOrder":2,"gameId":"0021600596","gameTimeUTC":"2017-01-14T01:00:00Z","gameEt":"2017-01-13T20:00:00Z","gameStatus":3,"gameStatusText":"Final","gameClock":"PT00M00.00S","broadcasterVideoLink":null,"awayTeam":{"teamId":1610612760,"teamCity":"Oklahoma City","teamName":"Thunder","teamTricode":"OKC","teamSlug":"thunder","score":86,"wins":24,"losses":17},"homeTeam":{"teamId":1610612750,"teamCity":"Minnesota","teamName":"Timberwolves","teamTricode":"MIN","teamSlug":"timberwolves","score":96,"wins":14,"losses":26}},{"recencyOrder":3,"gameId":"0021600459","gameTimeUTC":"2016-12-26T01:00:00Z","gameEt":"2016-12-25T20:00:00Z","gameStatus":3,"gameStatusText":"Final","gameClock":"PT00M00.00S","broadcasterVideoLink":null,"awayTeam":{"teamId":1610612750,"teamCity":"Minnesota","teamName":"Timberwolves","teamTricode":"MIN","teamSlug":"timberwolves","score":100,"wins":9,"losses":21},"homeTeam":{"teamId":1610612760,"teamCity":"Oklahoma City","teamName":"Thunder","teamTricode":"OKC","teamSlug":"thunder","score":112,"wins":19,"losses":12}},{"recencyOrder":4,"gameId":"0021600079","gameTimeUTC":"2016-11-05T22:00:00Z","gameEt":"2016-11-05T18:00:00Z","gameStatus":3,"gameStatusText":"Final","gameClock":"PT00M00.00S","broadcasterVideoLink":null,"awayTeam":{"teamId":1610612750,"teamCity":"Minnesota","teamName":"Timberwolves","teamTricode":"MIN","teamSlug":"timberwolves","score":92,"wins":1,"losses":4},"homeTeam":{"teamId":1610612760,"teamCity":"Oklahoma City","teamName":"Thunder","teamTricode":"OKC","teamSlug":"thunder","score":112,"wins":5,"losses":1}},{"recencyOrder":5,"gameId":"0021500968","gameTimeUTC":"2016-03-12T01:00:00Z","gameEt":"2016-03-11T20:00:00Z","gameStatus":3,"gameStatusText":"Final","gameClock":"PT00M00.00S","broadcasterVideoLink":null,"awayTeam":{"teamId":1610612750,"teamCity":"Minnesota","teamName":"Timberwolves","teamTricode":"MIN","teamSlug":"timberwolves","score":99,"wins":21,"losses":45},"homeTeam":{"teamId":1610612760,"teamCity":"Oklahoma City","teamName":"Thunder","teamTricode":"OKC","teamSlug":"thunder","score":96,"wins":44,"losses":21}}]},"pregameCharts":{"homeTeam":{"teamId":1610612760,"teamCity":"Oklahoma City","teamName":"Thunder","teamTricode":"OKC","statistics":{"points":107.9,"reboundsTotal":45.1,"assists":21.3,"steals":9.1,"blocks":5,"turnovers":13.4,"fieldGoalsPercentage":0.453,"threePointersPercentage":0.354,"freeThrowsPercentage":0.716,"pointsInThePaint":43.9,"pointsSecondChance":15,"pointsFastBreak":15.2,"playerPtsLeaderFirstName":"Russell","playerPtsLeaderFamilyName":"Westbrook","playerPtsLeaderId":201566,"playerPtsLeaderPts":25.4,"playerRebLeaderFirstName":"Russell","playerRebLeaderFamilyName":"Westbrook","playerRebLeaderId":201566,"playerRebLeaderReb":10.1,"playerAstLeaderFirstName":"Russell","playerAstLeaderFamilyName":"Westbrook","playerAstLeaderId":201566,"playerAstLeaderAst":10.3,"playerBlkLeaderFirstName":"Steven","playerBlkLeaderFamilyName":"Adams","playerBlkLeaderId":203500,"playerBlkLeaderBlk":1.03}},"awayTeam":{"teamId":1610612750,"teamCity":"Minnesota","teamName":"Timberwolves","teamTricode":"MIN","statistics":{"points":109.5,"reboundsTotal":42,"assists":22.7,"steals":8.4,"blocks":4.2,"turnovers":11.7,"fieldGoalsPercentage":0.476,"threePointersPercentage":0.357,"freeThrowsPercentage":0.804,"pointsInThePaint":49.2,"pointsSecondChance":13.6,"pointsFastBreak":9.7,"playerPtsLeaderFirstName":"Jimmy","playerPtsLeaderFamilyName":"Butler","playerPtsLeaderId":202710,"playerPtsLeaderPts":22.2,"playerRebLeaderFirstName":"Karl-Anthony","playerRebLeaderFamilyName":"Towns","playerRebLeaderId":1626157,"playerRebLeaderReb":12.3,"playerAstLeaderFirstName":"Jeff","playerAstLeaderFamilyName":"Teague","playerAstLeaderId":201952,"playerAstLeaderAst":7,"playerBlkLeaderFirstName":"Karl-Anthony","playerBlkLeaderFamilyName":"Towns","playerBlkLeaderId":1626157,"playerBlkLeaderBlk":1.4}}},"postgameCharts":{"homeTeam":{"teamId":1610612760,"teamCity":"Oklahoma City","teamName":"Thunder","teamTricode":"OKC","statistics":{"points":113,"reboundsTotal":36,"assists":26,"steals":9,"blocks":6,"turnovers":11,"fieldGoalsPercentage":0.479,"threePointersPercentage":0.355,"freeThrowsPercentage":0.625,"pointsInThePaint":60,"pointsSecondChance":14,"pointsFastBreak":20,"biggestLead":3,"leadChanges":9,"timesTied":2,"biggestScoringRun":8,"turnoversTeam":0,"turnoversTotal":11,"reboundsTeam":9,"pointsFromTurnovers":23,"benchPoints":28,"playerPtsLeaderFirstName":"Russell","playerPtsLeaderFamilyName":"Westbrook","playerPtsLeaderId":201566,"playerPtsLeaderPts":31,"playerRebLeaderFirstName":"Steven","playerRebLeaderFamilyName":"Adams","playerRebLeaderId":203500,"playerRebLeaderReb":13,"playerAstLeaderFirstName":"Russell","playerAstLeaderFamilyName":"Westbrook","playerAstLeaderId":201566,"playerAstLeaderAst":10,"playerBlkLeaderFirstName":"Josh","playerBlkLeaderFamilyName":"Huestis","playerBlkLeaderId":203962,"playerBlkLeaderBlk":2}},"awayTeam":{"teamId":1610612750,"teamCity":"Minnesota","teamName":"Timberwolves","teamTricode":"MIN","statistics":{"points":115,"reboundsTotal":45,"assists":25,"steals":5,"blocks":1,"turnovers":17,"fieldGoalsPercentage":0.5,"threePointersPercentage":0.4,"freeThrowsPercentage":0.826,"pointsInThePaint":52,"pointsSecondChance":19,"pointsFastBreak":6,"biggestLead":14,"leadChanges":9,"timesTied":2,"biggestScoringRun":8,"turnoversTeam":1,"turnoversTotal":18,"reboundsTeam":13,"pointsFromTurnovers":13,"benchPoints":16,"playerPtsLeaderFirstName":"Karl-Anthony","playerPtsLeaderFamilyName":"Towns","playerPtsLeaderId":1626157,"playerPtsLeaderPts":27,"playerRebLeaderFirstName":"Karl-Anthony","playerRebLeaderFamilyName":"Towns","playerRebLeaderId":1626157,"playerRebLeaderReb":12,"playerAstLeaderFirstName":"Jeff","playerAstLeaderFamilyName":"Teague","playerAstLeaderId":201952,"playerAstLeaderAst":9,"playerBlkLeaderFirstName":"Karl-Anthony","playerBlkLeaderFamilyName":"Towns","playerBlkLeaderId":1626157,"playerBlkLeaderBlk":1}}},"videoAvailableFlag":1,"ptAvailable":1,"ptXYZAvailable":0,"whStatus":1,"hustleStatus":1,"historicalStatus":0,"gameSubtype":"","branchUrl":"gametime://games","ogImage":null,"hideLineScores":false,"hideGameCharts":false,"hideLeadTracker":false,"homeTeamPlayers":[{"personId":203518,"name":"Alex Abrines","nameI":"A. Abrines","firstName":"Alex","familyName":"Abrines","jerseyNum":"8"},{"personId":202331,"name":"Paul George","nameI":"P. George","firstName":"Paul","familyName":"George","jerseyNum":"13"},{"personId":203924,"name":"Jerami Grant","nameI":"J. Grant","firstName":"Jerami","familyName":"Grant","jerseyNum":"9"},{"personId":203500,"name":"Steven Adams","nameI":"S. Adams","firstName":"Steven","familyName":"Adams","jerseyNum":"12"},{"personId":203962,"name":"Josh Huestis","nameI":"J. Huestis","firstName":"Josh","familyName":"Huestis","jerseyNum":"34"},{"personId":203460,"name":"Andre Roberson","nameI":"A. Roberson","firstName":"Andre","familyName":"Roberson","jerseyNum":"21"},{"personId":202335,"name":"Patrick Patterson","nameI":"P. Patterson","firstName":"Patrick","familyName":"Patterson","jerseyNum":"54"},{"personId":2555,"name":"Nick Collison","nameI":"N. Collison","firstName":"Nick","familyName":"Collison","jerseyNum":"4"},{"personId":1626177,"name":"Dakari Johnson","nameI":"D. Johnson","firstName":"Dakari","familyName":"Johnson","jerseyNum":"44"},{"personId":201566,"name":"Russell Westbrook","nameI":"R. Westbrook","firstName":"Russell","familyName":"Westbrook","jerseyNum":"0"},{"personId":2546,"name":"Carmelo Anthony","nameI":"C. Anthony","firstName":"Carmelo","familyName":"Anthony","jerseyNum":"7"},{"personId":1628390,"name":"Terrance Ferguson","nameI":"T. Ferguson","firstName":"Terrance","familyName":"Ferguson","jerseyNum":"23"},{"personId":101109,"name":"Raymond Felton","nameI":"R. Felton","firstName":"Raymond","familyName":"Felton","jerseyNum":"2"}],"awayTeamPlayers":[{"personId":202357,"name":"Nemanja Bjelica","nameI":"N. Bjelica","firstName":"Nemanja","familyName":"Bjelica","jerseyNum":"8"},{"personId":203952,"name":"Andrew Wiggins","nameI":"A. Wiggins","firstName":"Andrew","familyName":"Wiggins","jerseyNum":"22"},{"personId":201952,"name":"Jeff Teague","nameI":"J. Teague","firstName":"Jeff","familyName":"Teague","jerseyNum":"0"},{"personId":1627875,"name":"Marcus Georges-Hunt","nameI":"M. Georges-Hunt","firstName":"Marcus","familyName":"Georges-Hunt","jerseyNum":"13"},{"personId":202332,"name":"Cole Aldrich","nameI":"C. Aldrich","firstName":"Cole","familyName":"Aldrich","jerseyNum":"45"},{"personId":203498,"name":"Shabazz Muhammad","nameI":"S. Muhammad","firstName":"Shabazz","familyName":"Muhammad","jerseyNum":"15"},{"personId":1626157,"name":"Karl-Anthony Towns","nameI":"K. Towns","firstName":"Karl-Anthony","familyName":"Towns","jerseyNum":"32"},{"personId":1626145,"name":"Tyus Jones","nameI":"T. Jones","firstName":"Tyus","familyName":"Jones","jerseyNum":"1"},{"personId":203476,"name":"Gorgui Dieng","nameI":"G. Dieng","firstName":"Gorgui","familyName":"Dieng","jerseyNum":"5"},{"personId":201959,"name":"Taj Gibson","nameI":"T. Gibson","firstName":"Taj","familyName":"Gibson","jerseyNum":"67"},{"personId":202710,"name":"Jimmy Butler","nameI":"J. Butler","firstName":"Jimmy","familyName":"Butler","jerseyNum":"23"},{"personId":201166,"name":"Aaron Brooks","nameI":"A. Brooks","firstName":"Aaron","familyName":"Brooks","jerseyNum":"30"},{"personId":2037,"name":"Jamal Crawford","nameI":"J. Crawford","firstName":"Jamal","familyName":"Crawford","jerseyNum":"11"}],"hyperlinks":[],"pbOdds":{},"gameRecap":null,"gameState":3}}